[
	{
		"e_id":"建筑施工场地a",
		"e_description": "济宁城市展示馆对面----太白湖附近",
		"e_our_name":"富慧源",
		"e_type": 0,
		"pm25a" :37.18,
		"pm10a" :94.36,
		"pm25b" :33.64,
		"pm10b" :58.71
	},
	{
		"e_id":"建筑施工场地b",
		"e_description": "泰白里营销中心附近",
		"e_our_name":"张马社区",
		"e_type": 0,
		"pm25a" :20.40,
		"pm10a" :65.45,
		"pm25b" :27.67,
		"pm10b" :49
	},
	{
		"e_id":"建筑垃圾堆放场c",
		"e_description": "鲁抗厂---中海城附近",
		"e_our_name":"中海城回填",
		"e_type": 1,
		"pm25a" : 19.24,
		"pm10a" : 70.03,
		"pm25b" : 30.88,
		"pm10b" : 42.83
	},
	{
		"e_id":"建筑垃圾消纳场d",
		"e_description": "中森环保资源厂",
		"e_our_name":"济徽高速东段处置地",
		"e_type": 1,
		"pm25a" : 34.47,
		"pm10a" : 135.05,
		"pm25b" : 24.96,
		"pm10b" : 36.17
	},
	{
		"e_id":"建筑垃圾堆放场e",
		"e_description": "济州古城香樟园旁",
		"e_our_name":"保利回填",
		"e_type": 1,
		"pm25a" : 31.73,
		"pm10a" : 114.61,
		"pm25b" : 24.13,
		"pm10b" : 38.87
	},
	{
		"e_id":"建筑垃圾堆放场f",
		"e_description": "济宁五里营河北村",
		"e_our_name":"人民医院西院区附近回填",
		"e_type": 1,
		"pm25a" :19.70,
		"pm10a" :81.43,
		"pm25b" :27.43,
		"pm10b" :46.7
	}
]
	
